<annotation>
	<folder>forest_fire</folder>
	<filename>2502ec63-7313-4c5b-aa6a-53dc14aa1a9d.jpg</filename>
	<path>F:\DataSets\hlw_fire_data\forest_fire\2502ec63-7313-4c5b-aa6a-53dc14aa1a9d.jpg</path>
	<source>
		<database>Unknown</database>
	</source>
	<size>
		<width>500</width>
		<height>350</height>
		<depth>3</depth>
	</size>
	<segmented>0</segmented>
	<object>
		<name>fire</name>
		<pose>Unspecified</pose>
		<truncated>0</truncated>
		<difficult>0</difficult>
		<bndbox>
			<xmin>307</xmin>
			<ymin>10</ymin>
			<xmax>382</xmax>
			<ymax>167</ymax>
		</bndbox>
	</object>
	<object>
		<name>fire</name>
		<pose>Unspecified</pose>
		<truncated>0</truncated>
		<difficult>0</difficult>
		<bndbox>
			<xmin>81</xmin>
			<ymin>228</ymin>
			<xmax>296</xmax>
			<ymax>297</ymax>
		</bndbox>
	</object>
	<object>
		<name>fire</name>
		<pose>Unspecified</pose>
		<truncated>0</truncated>
		<difficult>0</difficult>
		<bndbox>
			<xmin>400</xmin>
			<ymin>73</ymin>
			<xmax>484</xmax>
			<ymax>116</ymax>
		</bndbox>
	</object>
</annotation>
