<annotation>
	<folder>vehicle_fire</folder>
	<filename>716d1580-1327-4f30-ae57-2258161a59e6.jpg</filename>
	<path>F:\DataSets\hlw_fire_data\vehicle_fire\716d1580-1327-4f30-ae57-2258161a59e6.jpg</path>
	<source>
		<database>Unknown</database>
	</source>
	<size>
		<width>600</width>
		<height>400</height>
		<depth>3</depth>
	</size>
	<segmented>0</segmented>
	<object>
		<name>fire</name>
		<pose>Unspecified</pose>
		<truncated>0</truncated>
		<difficult>0</difficult>
		<bndbox>
			<xmin>64</xmin>
			<ymin>78</ymin>
			<xmax>590</xmax>
			<ymax>338</ymax>
		</bndbox>
	</object>
</annotation>
