<annotation>
	<folder>forest_fire</folder>
	<filename>8157d25d-a52b-43cf-ac5b-254373d8a2e6.jpg</filename>
	<path>F:\DataSets\hlw_fire_data\forest_fire\8157d25d-a52b-43cf-ac5b-254373d8a2e6.jpg</path>
	<source>
		<database>Unknown</database>
	</source>
	<size>
		<width>540</width>
		<height>347</height>
		<depth>3</depth>
	</size>
	<segmented>0</segmented>
	<object>
		<name>fire</name>
		<pose>Unspecified</pose>
		<truncated>0</truncated>
		<difficult>0</difficult>
		<bndbox>
			<xmin>197</xmin>
			<ymin>274</ymin>
			<xmax>222</xmax>
			<ymax>310</ymax>
		</bndbox>
	</object>
	<object>
		<name>fire</name>
		<pose>Unspecified</pose>
		<truncated>0</truncated>
		<difficult>0</difficult>
		<bndbox>
			<xmin>256</xmin>
			<ymin>180</ymin>
			<xmax>279</xmax>
			<ymax>208</ymax>
		</bndbox>
	</object>
	<object>
		<name>fire</name>
		<pose>Unspecified</pose>
		<truncated>0</truncated>
		<difficult>0</difficult>
		<bndbox>
			<xmin>229</xmin>
			<ymin>253</ymin>
			<xmax>241</xmax>
			<ymax>275</ymax>
		</bndbox>
	</object>
</annotation>
