<annotation>
	<folder>grassland_fire</folder>
	<filename>9e3176e1-ad75-4ef2-9d1f-80ef7c49ffa6.jpg</filename>
	<path>F:\DataSets\hlw_fire_data\grassland_fire\9e3176e1-ad75-4ef2-9d1f-80ef7c49ffa6.jpg</path>
	<source>
		<database>Unknown</database>
	</source>
	<size>
		<width>900</width>
		<height>675</height>
		<depth>3</depth>
	</size>
	<segmented>0</segmented>
	<object>
		<name>fire</name>
		<pose>Unspecified</pose>
		<truncated>0</truncated>
		<difficult>0</difficult>
		<bndbox>
			<xmin>318</xmin>
			<ymin>316</ymin>
			<xmax>383</xmax>
			<ymax>435</ymax>
		</bndbox>
	</object>
	<object>
		<name>fire</name>
		<pose>Unspecified</pose>
		<truncated>0</truncated>
		<difficult>0</difficult>
		<bndbox>
			<xmin>15</xmin>
			<ymin>513</ymin>
			<xmax>388</xmax>
			<ymax>598</ymax>
		</bndbox>
	</object>
</annotation>
