<annotation>
	<folder>building_fire</folder>
	<filename>9f639d29-46e7-4bb4-8a09-cf71444955ba.jpg</filename>
	<path>F:\DataSets\hlw_fire_data\building_fire\9f639d29-46e7-4bb4-8a09-cf71444955ba.jpg</path>
	<source>
		<database>Unknown</database>
	</source>
	<size>
		<width>484</width>
		<height>600</height>
		<depth>3</depth>
	</size>
	<segmented>0</segmented>
	<object>
		<name>fire</name>
		<pose>Unspecified</pose>
		<truncated>0</truncated>
		<difficult>0</difficult>
		<bndbox>
			<xmin>289</xmin>
			<ymin>178</ymin>
			<xmax>308</xmax>
			<ymax>471</ymax>
		</bndbox>
	</object>
	<object>
		<name>fire</name>
		<pose>Unspecified</pose>
		<truncated>0</truncated>
		<difficult>0</difficult>
		<bndbox>
			<xmin>299</xmin>
			<ymin>101</ymin>
			<xmax>337</xmax>
			<ymax>161</ymax>
		</bndbox>
	</object>
</annotation>
