<annotation>
	<folder>forest_fire</folder>
	<filename>acacc182-7eaf-490b-b29b-b8bea0877863.jpg</filename>
	<path>F:\DataSets\hlw_fire_data\forest_fire\acacc182-7eaf-490b-b29b-b8bea0877863.jpg</path>
	<source>
		<database>Unknown</database>
	</source>
	<size>
		<width>1000</width>
		<height>634</height>
		<depth>3</depth>
	</size>
	<segmented>0</segmented>
	<object>
		<name>fire</name>
		<pose>Unspecified</pose>
		<truncated>0</truncated>
		<difficult>0</difficult>
		<bndbox>
			<xmin>415</xmin>
			<ymin>423</ymin>
			<xmax>682</xmax>
			<ymax>607</ymax>
		</bndbox>
	</object>
	<object>
		<name>fire</name>
		<pose>Unspecified</pose>
		<truncated>0</truncated>
		<difficult>0</difficult>
		<bndbox>
			<xmin>277</xmin>
			<ymin>429</ymin>
			<xmax>431</xmax>
			<ymax>507</ymax>
		</bndbox>
	</object>
	<object>
		<name>fire</name>
		<pose>Unspecified</pose>
		<truncated>0</truncated>
		<difficult>0</difficult>
		<bndbox>
			<xmin>200</xmin>
			<ymin>559</ymin>
			<xmax>281</xmax>
			<ymax>591</ymax>
		</bndbox>
	</object>
</annotation>
