<annotation>
	<folder>building_fire</folder>
	<filename>e2d48657-fb6c-478b-ae89-9a0409bbcd39.jpg</filename>
	<path>F:\DataSets\hlw_fire_data\building_fire\e2d48657-fb6c-478b-ae89-9a0409bbcd39.jpg</path>
	<source>
		<database>Unknown</database>
	</source>
	<size>
		<width>600</width>
		<height>399</height>
		<depth>3</depth>
	</size>
	<segmented>0</segmented>
	<object>
		<name>fire</name>
		<pose>Unspecified</pose>
		<truncated>0</truncated>
		<difficult>0</difficult>
		<bndbox>
			<xmin>193</xmin>
			<ymin>104</ymin>
			<xmax>207</xmax>
			<ymax>123</ymax>
		</bndbox>
	</object>
	<object>
		<name>fire</name>
		<pose>Unspecified</pose>
		<truncated>0</truncated>
		<difficult>0</difficult>
		<bndbox>
			<xmin>194</xmin>
			<ymin>164</ymin>
			<xmax>209</xmax>
			<ymax>183</ymax>
		</bndbox>
	</object>
</annotation>
