<annotation>
	<folder>forest_fire</folder>
	<filename>e3ddfdd2-d7cc-4aa8-a542-a2bcf27ed6c8.jpg</filename>
	<path>F:\DataSets\hlw_fire_data\forest_fire\e3ddfdd2-d7cc-4aa8-a542-a2bcf27ed6c8.jpg</path>
	<source>
		<database>Unknown</database>
	</source>
	<size>
		<width>545</width>
		<height>315</height>
		<depth>3</depth>
	</size>
	<segmented>0</segmented>
	<object>
		<name>fire</name>
		<pose>Unspecified</pose>
		<truncated>0</truncated>
		<difficult>0</difficult>
		<bndbox>
			<xmin>76</xmin>
			<ymin>133</ymin>
			<xmax>524</xmax>
			<ymax>205</ymax>
		</bndbox>
	</object>
	<object>
		<name>fire</name>
		<pose>Unspecified</pose>
		<truncated>0</truncated>
		<difficult>0</difficult>
		<bndbox>
			<xmin>90</xmin>
			<ymin>252</ymin>
			<xmax>128</xmax>
			<ymax>279</ymax>
		</bndbox>
	</object>
</annotation>
