<annotation>
	<folder>forest_fire</folder>
	<filename>eb5142a4-c8a1-4b18-8362-19887dd54de0.jpg</filename>
	<path>F:\DataSets\hlw_fire_data\forest_fire\eb5142a4-c8a1-4b18-8362-19887dd54de0.jpg</path>
	<source>
		<database>Unknown</database>
	</source>
	<size>
		<width>361</width>
		<height>239</height>
		<depth>3</depth>
	</size>
	<segmented>0</segmented>
	<object>
		<name>fire</name>
		<pose>Unspecified</pose>
		<truncated>0</truncated>
		<difficult>0</difficult>
		<bndbox>
			<xmin>113</xmin>
			<ymin>126</ymin>
			<xmax>260</xmax>
			<ymax>157</ymax>
		</bndbox>
	</object>
</annotation>
