<annotation>
	<folder>forest_fire</folder>
	<filename>f010ad63-4885-4c59-9f0f-9ed5246f1440.jpg</filename>
	<path>F:\DataSets\hlw_fire_data\forest_fire\f010ad63-4885-4c59-9f0f-9ed5246f1440.jpg</path>
	<source>
		<database>Unknown</database>
	</source>
	<size>
		<width>540</width>
		<height>340</height>
		<depth>3</depth>
	</size>
	<segmented>0</segmented>
	<object>
		<name>fire</name>
		<pose>Unspecified</pose>
		<truncated>0</truncated>
		<difficult>0</difficult>
		<bndbox>
			<xmin>31</xmin>
			<ymin>179</ymin>
			<xmax>83</xmax>
			<ymax>217</ymax>
		</bndbox>
	</object>
	<object>
		<name>fire</name>
		<pose>Unspecified</pose>
		<truncated>0</truncated>
		<difficult>0</difficult>
		<bndbox>
			<xmin>187</xmin>
			<ymin>201</ymin>
			<xmax>229</xmax>
			<ymax>241</ymax>
		</bndbox>
	</object>
	<object>
		<name>fire</name>
		<pose>Unspecified</pose>
		<truncated>0</truncated>
		<difficult>0</difficult>
		<bndbox>
			<xmin>359</xmin>
			<ymin>210</ymin>
			<xmax>421</xmax>
			<ymax>269</ymax>
		</bndbox>
	</object>
	<object>
		<name>fire</name>
		<pose>Unspecified</pose>
		<truncated>0</truncated>
		<difficult>0</difficult>
		<bndbox>
			<xmin>284</xmin>
			<ymin>228</ymin>
			<xmax>304</xmax>
			<ymax>250</ymax>
		</bndbox>
	</object>
</annotation>
