<annotation>
	<folder>Fire images</folder>
	<filename>your-room1.jpg</filename>
	<path>F:\DataSets\hlw_fire_data\Fire images\your-room1.jpg</path>
	<source>
		<database>Unknown</database>
	</source>
	<size>
		<width>434</width>
		<height>480</height>
		<depth>3</depth>
	</size>
	<segmented>0</segmented>
	<object>
		<name>fire</name>
		<pose>Unspecified</pose>
		<truncated>0</truncated>
		<difficult>0</difficult>
		<bndbox>
			<xmin>242</xmin>
			<ymin>269</ymin>
			<xmax>304</xmax>
			<ymax>399</ymax>
		</bndbox>
	</object>
</annotation>
